grapheteria/__init__.py
grapheteria/build_hooks.py
grapheteria/utils.py
grapheteria/server/__init__.py
grapheteria/server/main.py
grapheteria/server/routes.py
grapheteria/server/workflow_manager.py
grapheteria/server/handlers/__init__.py
grapheteria/server/handlers/file_handlers.py
grapheteria/server/handlers/inbound_handler.py
grapheteria/server/handlers/outbound_handler.py
grapheteria/server/static/ui/index.html
grapheteria/server/static/ui/assets/index-2EKecwvU.js
grapheteria/server/static/ui/assets/index-BJUet-OD.css
grapheteria/server/utils/__init__.py
grapheteria/server/utils/scanner.py
grapheteria-0.0.0.dist-info/METADATA
grapheteria-0.0.0.dist-info/WHEEL
grapheteria-0.0.0.dist-info/entry_points.txt
grapheteria-0.0.0.dist-info/licenses/LICENSE
grapheteria-0.0.0.dist-info/RECORD
