Metadata-Version: 2.4
Name: grapheteria
Version: 0.0.0
Summary: A structured framework bringing uniformity to agent orchestration! 
Project-URL: Homepage, https://github.com/beubax/grapheteria
Project-URL: Documentation, https://github.com/beubax/grapheteria#readme
Project-URL: Issues, https://github.com/beubax/grapheteria/issues
Project-URL: Changelog, https://github.com/beubax/grapheteria/blob/main/CHANGELOG.md
Author-email: Tejas Ravishankar <tejas.ravishankar@gmail.com>
License: MIT
License-File: LICENSE
Keywords: agentic-ai,automation,workflow
Classifier: Development Status :: 4 - Beta
Classifier: Intended Audience :: Developers
Classifier: License :: OSI Approved :: MIT License
Classifier: Programming Language :: Python :: 3
Classifier: Programming Language :: Python :: 3.8
Classifier: Programming Language :: Python :: 3.9
Classifier: Programming Language :: Python :: 3.10
Classifier: Programming Language :: Python :: 3.11
Requires-Python: >=3.6
Requires-Dist: dill
Requires-Dist: fastapi
Requires-Dist: jinja2
Requires-Dist: libcst
Requires-Dist: uvicorn[standard]
Requires-Dist: watchdog
